submitr/__init__.py
submitr/base.py
submitr/exceptions.py
submitr/portal_network_access.py
submitr/scripts/__init__.py
submitr/scripts/check_submission.py
submitr/scripts/make_sample_fastq_file.py
submitr/scripts/resume_uploads.py
submitr/scripts/show_upload_info.py
submitr/scripts/submit_genelist.py
submitr/scripts/submit_metadata_bundle.py
submitr/scripts/submit_ontology.py
submitr/scripts/upload_item_data.py
submitr/submission.py
submitr/tests/__init__.py
submitr/tests/conftest_settings.py
submitr/tests/data/f1_R1.fastq.gz
submitr/tests/data/f1_R2.fastq.gz
submitr/tests/data/f2_R1.fastq.gz
submitr/tests/data/f2_R2.fastq.gz
submitr/tests/data/simulated_bundle.json
submitr/tests/data/submission_simple.xlsx
submitr/tests/data/submission_simple2.xlsx
submitr/tests/data/submission_test.xlsx
submitr/tests/data/submission_test_with_errors.xlsx
submitr/tests/data/test1_R1.fastq.gz
submitr/tests/data/test1_R2.fastq.gz
submitr/tests/test_base.py
submitr/tests/test_check_submission.py
submitr/tests/test_exceptions.py
submitr/tests/test_make_sample_fastq_file.py
submitr/tests/test_misc.py
submitr/tests/test_resume_uploads.py
submitr/tests/test_show_upload_info.py
submitr/tests/test_submission.py
submitr/tests/test_submit_genelist.py
submitr/tests/test_submit_metadata_bundle.py
submitr/tests/test_submit_ontology.py
submitr/tests/test_testing_helpers.py
submitr/tests/test_upload_item_data.py
submitr/tests/test_utils.py
submitr/tests/testing_helpers.py
submitr/utils.py
submitr-0.3.4.dist-info/LICENSE.txt
submitr-0.3.4.dist-info/METADATA
submitr-0.3.4.dist-info/WHEEL
submitr-0.3.4.dist-info/entry_points.txt
submitr-0.3.4.dist-info/RECORD
