Metadata-Version: 2.1
Name: submitr
Version: 0.3.4
Summary: Support for uploading file submissions to SMAHT.
Home-page: https://github.com/smaht-dac/submitr
License: MIT
Keywords: submitr,smaht
Author: 4DN-DCIC Team
Author-email: support@4dnucleome.org
Requires-Python: >=3.7.0,<3.10
Classifier: Development Status :: 4 - Beta
Classifier: Intended Audience :: Developers
Classifier: Intended Audience :: Science/Research
Classifier: License :: OSI Approved :: MIT License
Classifier: Natural Language :: English
Classifier: Programming Language :: Python :: 3
Classifier: Programming Language :: Python :: 3.7
Classifier: Programming Language :: Python :: 3.8
Classifier: Programming Language :: Python :: 3.9
Classifier: Programming Language :: Python :: 3
Classifier: Programming Language :: Python :: 3.7
Classifier: Programming Language :: Python :: 3.8
Classifier: Programming Language :: Python :: 3.9
Classifier: Topic :: Database :: Database Engines/Servers
Requires-Dist: PyYAML (==5.3.1)
Requires-Dist: awscli (>=1.27.79,<2.0.0)
Requires-Dist: dcicutils (>=7.7.1,<8.0.0)
Requires-Dist: requests (>=2.28.2,<3.0.0)
Project-URL: Repository, https://github.com/smaht-dac/submitr.git
